maia2/__init__.py
maia2/dataset.py
maia2/fetch_data.sh
maia2/inference.py
maia2/main.py
maia2/model.py
maia2/requirements.txt
maia2/train.py
maia2/utils.py
maia2-0.9.dist-info/LICENSE
maia2-0.9.dist-info/WHEEL
maia2-0.9.dist-info/METADATA
maia2-0.9.dist-info/RECORD
