Metadata-Version: 2.1
Name: maia2
Version: 0.9
Summary: An amazing sample package for maia2.
Author-email: csslab <josephtang@cs.toronto.edu>
Classifier: License :: OSI Approved :: MIT License
Project-URL: Home, https://github.com/CSSLab/maia2
